scrapemeagain/__init__.py
scrapemeagain/config.py
scrapemeagain/databaser.py
scrapemeagain/pipeline.py
scrapemeagain/dockerized/__init__.py
scrapemeagain/dockerized/docker-compose.yml
scrapemeagain/dockerized/ipchanger.py
scrapemeagain/dockerized/utils.py
scrapemeagain/dockerized/apps/__init__.py
scrapemeagain/dockerized/apps/datastore/__init__.py
scrapemeagain/dockerized/apps/datastore/client.py
scrapemeagain/dockerized/apps/datastore/server.py
scrapemeagain/dockerized/apps/healthcheck/__init__.py
scrapemeagain/dockerized/apps/healthcheck/server.py
scrapemeagain/dockerized/apps/healthcheck/test.py
scrapemeagain/dockerized/apps/ipstore/__init__.py
scrapemeagain/dockerized/apps/ipstore/client.py
scrapemeagain/dockerized/apps/ipstore/server.py
scrapemeagain/dockerized/apps/urlbroker/__init__.py
scrapemeagain/dockerized/apps/urlbroker/client.py
scrapemeagain/dockerized/apps/urlbroker/server.py
scrapemeagain/dockerized/apps/urlbroker/urlbrokers.py
scrapemeagain/dockerized/entrypoints/entrypoint.base.sh
scrapemeagain/dockerized/entrypoints/entrypoint.scp1.sh
scrapemeagain/dockerized/entrypoints/entrypoint.scpx.sh
scrapemeagain/scrapers/__init__.py
scrapemeagain/scrapers/basemodel.py
scrapemeagain/scrapers/basescraper.py
scrapemeagain/utils/__init__.py
scrapemeagain/utils/alnum.py
scrapemeagain/utils/http.py
scrapemeagain/utils/logger.py
scrapemeagain/utils/services.py
scrapemeagain/utils/useragents.py
scrapemeagain-1.0.5.data/scripts/scrapemeagain-compose.py
tests/__init__.py
tests/pipeline_base.py
tests/test_docker_compose.py
tests/test_pipeline.py
tests/utils.py
tests/integration/__init__.py
tests/integration/fake_config.py
tests/integration/fake_ipchanger.py
tests/integration/test_integration.py
scrapemeagain-1.0.5.dist-info/METADATA
scrapemeagain-1.0.5.dist-info/WHEEL
scrapemeagain-1.0.5.dist-info/top_level.txt
scrapemeagain-1.0.5.dist-info/RECORD
