Metadata-Version: 2.1
Name: scrapemeagain
Version: 1.0.5
Summary: Yet another Python web scraping application
Home-page: https://github.com/DusanMadar/ScrapeMeAgain
Author: Dusan Madar
Author-email: madar.dusan@gmail.com
License: MIT
Keywords: web scraper
Platform: linux
Classifier: Development Status :: 5 - Production/Stable
Classifier: Environment :: Web Environment
Classifier: Intended Audience :: Developers
Classifier: License :: OSI Approved :: MIT License
Classifier: Programming Language :: Python :: 3.6
Classifier: Topic :: Internet :: WWW/HTTP
Classifier: Topic :: Software Development :: Libraries :: Python Modules
Requires-Python: >=3.6
Requires-Dist: beautifulsoup4
Requires-Dist: requests
Requires-Dist: sqlalchemy
Requires-Dist: stem
Requires-Dist: flask
Requires-Dist: toripchanger
